interface
django_memdb_test
django_memdb
