Metadata-Version: 1.1
Name: django-memdb
Version: 0.0.6
Summary: Django Memory Database
Home-page: https://bitbucket.org/hellwig/django-memdb/
Author: Martin P. Hellwig
Author-email: martin.hellwig@gmail.com
License: BSD
Download-URL: https://bitbucket.org/hellwig/django-memdb/download/0.0.6.zip
Keywords: django,django-integrator
Platform: UNKNOWN
Classifier: Programming Language :: Python :: 3
